nhaystack/__init__.py
nhaystack/indexes.py
nhaystack/routers.py
nhaystack/signals.py
nhaystack/backends/__init__.py
nhaystack/backends/elasticsearch.py
nhaystack/utils/__init__.py
nhaystack/utils/connection_url.py
nhaystack/utils/languages.py
nhaystack/utils/test.py
nhaystack-0.0.6.dist-info/DESCRIPTION.rst
nhaystack-0.0.6.dist-info/METADATA
nhaystack-0.0.6.dist-info/RECORD
nhaystack-0.0.6.dist-info/WHEEL
nhaystack-0.0.6.dist-info/metadata.json
nhaystack-0.0.6.dist-info/top_level.txt
nhaystack-0.0.6.dist-info/zip-safe
