Metadata-Version: 2.0
Name: nhaystack
Version: 0.0.6
Summary: Improvements, optimizations and back-ports for Haystack (with Elastic biases).
Home-page: https://github.com/noveogroup/nhaystack
Author: Noveo Group
Author-email: evgeny.sizikov@noveogroup.com
License: BSD
Platform: UNKNOWN
Classifier: Development Status :: 4 - Beta
Classifier: Environment :: Web Environment
Classifier: Framework :: Django
Classifier: Intended Audience :: Developers
Classifier: License :: OSI Approved :: BSD License
Classifier: Operating System :: OS Independent
Classifier: Programming Language :: Python
Classifier: Programming Language :: Python :: 2
Classifier: Programming Language :: Python :: 2.7
Classifier: Programming Language :: Python :: 3
Classifier: Programming Language :: Python :: 3.4
Classifier: Programming Language :: Python :: 3.5
Classifier: Topic :: Utilities
Requires-Dist: Django (>=1.6)
